CHANGES.txt
DEPENDENCES.txt
README.txt
setup.py
src/ng/__init__.py
src/ng.zcmlmultiform.egg-info/PKG-INFO
src/ng.zcmlmultiform.egg-info/SOURCES.txt
src/ng.zcmlmultiform.egg-info/dependency_links.txt
src/ng.zcmlmultiform.egg-info/namespace_packages.txt
src/ng.zcmlmultiform.egg-info/not-zip-safe
src/ng.zcmlmultiform.egg-info/requires.txt
src/ng.zcmlmultiform.egg-info/top_level.txt
src/ng/zcmlmultiform/__init__.py
src/ng/zcmlmultiform/configure.zcml
src/ng/zcmlmultiform/interfaces.py
src/ng/zcmlmultiform/meta.zcml
src/ng/zcmlmultiform/metaconfigure.py
src/ng/zcmlmultiform/metadirectives.py
src/ng/zcmlmultiform/multiform.pt
src/ng/zcmlmultiform/multiform.py
src/ng/zcmlmultiform/multiformitem.pt
src/ng/zcmlmultiform/multiformitem.py
src/ng/zcmlmultiform/ng.zcmlmultiform.txt
src/ng/zcmlmultiform/viewletbase.py
src/ng/zcmlmultiform/etc/ng.zcmlmultiform-meta.zcml